trading_economics_calendar/__init__.py
trading_economics_calendar/client.py
trading_economics_calendar/server.py
trading_economics_calendar_mcp-0.1.0.dist-info/licenses/LICENSE
trading_economics_calendar_mcp-0.1.0.dist-info/METADATA
trading_economics_calendar_mcp-0.1.0.dist-info/WHEEL
trading_economics_calendar_mcp-0.1.0.dist-info/entry_points.txt
trading_economics_calendar_mcp-0.1.0.dist-info/top_level.txt
trading_economics_calendar_mcp-0.1.0.dist-info/RECORD
